[
   {
      "body":"In an unexpected turn of announcements, our brave troops are advancing without problems over the defenses of the Federated Suns.",
      "fromId":1,
      "karma":0,
      "time":1332627631000,
      "favorited":false,
      "subject":"The troops attacking New Syrtis!",
      "publishedIn":"Star of Sian",
      "fromName":"Kineas",
      "communicationId":1
   },
   {
      "body":"Our troops are currently playing some war games in turtle bay. We encourage our citizens not to move over there during the next days.",
      "fromId":2,
      "karma":0,
      "time":1332627631000,
      "favorited":false,
      "subject":"Our troops exercising in New Syrtis",
      "publishedIn":"Herald of New Syrtis",
      "fromName":"Vitor",
      "communicationId":2
   }
]